<annotation>
  <folder>Datacluster</folder>
  <filename>Datacluster_Labs_Suitcase (80).jpg</filename>
  <source>
    <database>Unknown</database>
    <annotation>Unknown</annotation>
    <image>Unknown</image>
  </source>
  <size>
    <width>3000</width>
    <height>4000</height>
    <depth></depth>
  </size>
  <segmented>0</segmented>
  <object>
    <name>suitcase</name>
    <truncated>0</truncated>
    <occluded>0</occluded>
    <difficult>0</difficult>
    <bndbox>
      <xmin>499.84</xmin>
      <ymin>888.76</ymin>
      <xmax>2441.21</xmax>
      <ymax>3435.99</ymax>
    </bndbox>
    <attributes>
      <attribute>
        <name>rotation</name>
        <value>0.0</value>
      </attribute>
    </attributes>
  </object>
</annotation>
